jams/__init__.py
jams/core.py
jams/display.py
jams/eval.py
jams/exceptions.py
jams/nsconvert.py
jams/schema.py
jams/sonify.py
jams/util.py
jams/version.py
jams/schemata/jams_schema.json
jams/schemata/namespaces/beat/beat.json
jams/schemata/namespaces/beat/position.json
jams/schemata/namespaces/chord/chord.json
jams/schemata/namespaces/chord/harte.json
jams/schemata/namespaces/chord/roman.json
jams/schemata/namespaces/key/key_mode.json
jams/schemata/namespaces/lyrics/bow.json
jams/schemata/namespaces/lyrics/lyrics.json
jams/schemata/namespaces/misc/blob.json
jams/schemata/namespaces/misc/scaper.json
jams/schemata/namespaces/misc/vector.json
jams/schemata/namespaces/mood/thayer.json
jams/schemata/namespaces/onset/onset.json
jams/schemata/namespaces/pattern/jku.json
jams/schemata/namespaces/pitch/class.json
jams/schemata/namespaces/pitch/contour_hz.json
jams/schemata/namespaces/pitch/hz.json
jams/schemata/namespaces/pitch/midi.json
jams/schemata/namespaces/pitch/note_hz.json
jams/schemata/namespaces/pitch/note_midi.json
jams/schemata/namespaces/segment/multi.json
jams/schemata/namespaces/segment/open.json
jams/schemata/namespaces/segment/salami_function.json
jams/schemata/namespaces/segment/salami_lower.json
jams/schemata/namespaces/segment/salami_upper.json
jams/schemata/namespaces/segment/tut.json
jams/schemata/namespaces/tag/cal10k.json
jams/schemata/namespaces/tag/cal500.json
jams/schemata/namespaces/tag/gtzan.json
jams/schemata/namespaces/tag/medleydb_instruments.json
jams/schemata/namespaces/tag/msd_tagtraum_cd1.json
jams/schemata/namespaces/tag/msd_tagtraum_cd2.json
jams/schemata/namespaces/tag/open.json
jams/schemata/namespaces/tag/tag_audioset.json
jams/schemata/namespaces/tag/tag_audioset_genre.json
jams/schemata/namespaces/tag/tag_audioset_instruments.json
jams/schemata/namespaces/tag/tag_fma_genre.json
jams/schemata/namespaces/tag/tag_fma_subgenre.json
jams/schemata/namespaces/tag/tag_urbansound.json
jams/schemata/namespaces/tempo/tempo.json
jams-0.3.5.dist-info/licenses/LICENSE
jams-0.3.5.dist-info/METADATA
jams-0.3.5.dist-info/WHEEL
jams-0.3.5.dist-info/top_level.txt
jams-0.3.5.dist-info/RECORD
