Metadata-Version: 2.4
Name: jams
Version: 0.3.5
Summary: JAMS: A JSON Audio Metadata Standard
Home-page: https://github.com/marl/jams
Download-URL: https://github.com/marl/jams/releases
Author: JAMS development crew
License: ISC
Classifier: Programming Language :: Python
Classifier: Development Status :: 3 - Alpha
Classifier: Intended Audience :: Developers
Classifier: Topic :: Multimedia :: Sound/Audio :: Analysis
Classifier: Programming Language :: Python :: 3
Classifier: Programming Language :: Python :: 3.9
Classifier: Programming Language :: Python :: 3.10
Classifier: Programming Language :: Python :: 3.11
Classifier: Programming Language :: Python :: 3.12
Classifier: Programming Language :: Python :: 3.13
License-File: LICENSE
Requires-Dist: numpy>=1.20.0
Requires-Dist: jsonschema>=4.0.1
Requires-Dist: pandas>=1.2.0
Requires-Dist: mir_eval>=0.8.2
Requires-Dist: sortedcontainers>=2.1.0
Requires-Dist: six
Requires-Dist: decorator
Provides-Extra: display
Requires-Dist: matplotlib>=3.4.1; extra == "display"
Provides-Extra: tests
Requires-Dist: pytest~=8.0; extra == "tests"
Requires-Dist: pytest-cov; extra == "tests"
Requires-Dist: matplotlib>=3.4.1; extra == "tests"
Provides-Extra: docs
Requires-Dist: numpydoc; extra == "docs"
Requires-Dist: sphinx_rtd_theme; extra == "docs"
Dynamic: download-url
Dynamic: license-file
